platepy/__init__.py
platepy/_getGaussQuadrature.py
platepy/_internalForces.py
platepy/_localMatrixes.py
platepy/_rotationMatrix.py
platepy/_shapeFunctions.py
platepy/_slicingFunctions.py
platepy/analyticPlateSolutions.py
platepy/createModel.py
platepy/displayModel.py
platepy/generateMesh.py
platepy/solveModel.py
platepy/tutorials/demo1.py
platepy/tutorials/demo2.py
platepy/tutorials/tutorial1.py
platepy/tutorials/tutorial2.py
platepy/tutorials/tutorial3.py
platepy/tutorials/tutorial4.py
platepy-1.0.5.dist-info/LICENCE
platepy-1.0.5.dist-info/METADATA
platepy-1.0.5.dist-info/WHEEL
platepy-1.0.5.dist-info/top_level.txt
platepy-1.0.5.dist-info/RECORD
