Metadata-Version: 2.1
Name: platepy
Version: 1.0.5
Summary: Create and compute plate models using FEM
Home-page: https://github.com/tobiadig/platepyProject
Author: Tobia Diggelmann
Author-email: tobiadig@gmail.com
License: UNKNOWN
Project-URL: Documentation, https://tobiadig.github.io/
Project-URL: Source Code, https://github.com/tobiadig/platepy
Platform: UNKNOWN
Classifier: Programming Language :: Python :: 3
Classifier: License :: OSI Approved :: GNU Affero General Public License v3 or later (AGPLv3+)
Classifier: Operating System :: OS Independent
Requires-Python: >=3.6
License-File: LICENCE
